pywebostv/__init__.py
pywebostv/connection.py
pywebostv/controls.py
pywebostv/discovery.py
pywebostv/model.py
pywebostv-0.8.4.dist-info/LICENSE
pywebostv-0.8.4.dist-info/METADATA
pywebostv-0.8.4.dist-info/WHEEL
pywebostv-0.8.4.dist-info/top_level.txt
pywebostv-0.8.4.dist-info/RECORD
