Metadata-Version: 2.1
Name: pywebostv
Version: 0.8.4
Summary: Library to remote control LG Web OS TV
Home-page: https://github.com/supersaiyanmode/PyWebOSTV
Author: Srivatsan Iyer
Author-email: supersaiyanmode.rox@gmail.com
License: MIT
Platform: UNKNOWN
Requires-Dist: ws4py
Requires-Dist: requests[security]
Requires-Dist: future
